octoploy/__init__.py
octoploy/octoploy.py
octoploy/api/Kubectl.py
octoploy/api/Model.py
octoploy/api/__init__.py
octoploy/backup/BackupGenerator.py
octoploy/backup/__init__.py
octoploy/config/AppConfig.py
octoploy/config/BaseConfig.py
octoploy/config/Config.py
octoploy/config/DeploymentActionConfig.py
octoploy/config/DynamicConfigMap.py
octoploy/config/YmlConfig.py
octoploy/config/__init__.py
octoploy/converter/HelmToOcto.py
octoploy/converter/__init__.py
octoploy/deploy/AppDeploy.py
octoploy/deploy/DeploymentBundle.py
octoploy/deploy/DeploymentMode.py
octoploy/deploy/K8sObjectDeployer.py
octoploy/deploy/__init__.py
octoploy/k8s/BaseObj.py
octoploy/k8s/K8sObjectDiff.py
octoploy/k8s/SecretObj.py
octoploy/k8s/__init__.py
octoploy/processing/Constants.py
octoploy/processing/DataDiff.py
octoploy/processing/DataPreProcessor.py
octoploy/processing/DecryptionProcessor.py
octoploy/processing/K8sObjectMerge.py
octoploy/processing/NamespaceProcessor.py
octoploy/processing/TreeWalker.py
octoploy/processing/ValueLoader.py
octoploy/processing/YmlTemplateProcessor.py
octoploy/processing/__init__.py
octoploy/state/StateMover.py
octoploy/state/StateTracking.py
octoploy/state/__init__.py
octoploy/utils/Cert.py
octoploy/utils/DictUtils.py
octoploy/utils/Encryption.py
octoploy/utils/Errors.py
octoploy/utils/Log.py
octoploy/utils/Utils.py
octoploy/utils/Yml.py
octoploy/utils/YmlWriter.py
octoploy/utils/__init__.py
octoploy-1.4.0.dist-info/licenses/LICENSE
tests/AppDeploymentTest.py
tests/DictUtilsTest.py
tests/K8sObjectDiffTest.py
tests/OcObjectMergeTest.py
tests/StateTrackingTest.py
tests/TestUtils.py
tests/YmlTempalteProcessorTest.py
tests/__init__.py
tests/config/AppConfigTest.py
tests/config/__init__.py
tests/processing/ValueLoaderTest.py
tests/processing/__init__.py
tests/utils/EncryptionTest.py
tests/utils/YmlWriterTest.py
tests/utils/__init__.py
octoploy-1.4.0.dist-info/METADATA
octoploy-1.4.0.dist-info/WHEEL
octoploy-1.4.0.dist-info/entry_points.txt
octoploy-1.4.0.dist-info/top_level.txt
octoploy-1.4.0.dist-info/RECORD
