Metadata-Version: 2.4
Name: octoploy
Version: 1.4.0
Summary: Simple kubernetes / openshift templating engine with templating, libraries, state tracking
Home-page: https://github.com/davidgiga1993/octoploy
Author: davidgiga1993
Author-email: david@dev-core.org
Classifier: Development Status :: 4 - Beta
Classifier: Programming Language :: Python :: 3
Classifier: License :: OSI Approved :: MIT License
Classifier: Operating System :: OS Independent
Classifier: Topic :: Software Development :: Libraries
Requires-Python: >=3.8
License-File: LICENSE
Requires-Dist: pyyaml
Requires-Dist: pycryptodome
Dynamic: author
Dynamic: author-email
Dynamic: classifier
Dynamic: description
Dynamic: description-content-type
Dynamic: home-page
Dynamic: license-file
Dynamic: requires-dist
Dynamic: requires-python
Dynamic: summary
